Metadata-Version: 2.1
Name: snapcode
Version: 0.0.3
Summary: Extract code blocks from screenshots and images
Home-page: https://github.com/Vishnunkumar/snapcode/
Author: Vishnu Nandakumar
Author-email: nkumarvishnu25@gmail.com
License: MIT license
Keywords: codesnap,nlp,cv,transformers
Classifier: Development Status :: 3 - Alpha
Classifier: Intended Audience :: Developers
Classifier: Topic :: Software Development :: Build Tools
Classifier: License :: OSI Approved :: MIT License
Classifier: Programming Language :: Python :: 3
Classifier: Programming Language :: Python :: 3.4
Classifier: Programming Language :: Python :: 3.5
Classifier: Programming Language :: Python :: 3.6
License-File: LICENSE
